hello_emoji/__init__.py
hello_emoji/example.py
hello_emoji-0.0.3.dist-info/LICENSE
hello_emoji-0.0.3.dist-info/METADATA
hello_emoji-0.0.3.dist-info/WHEEL
hello_emoji-0.0.3.dist-info/top_level.txt
hello_emoji-0.0.3.dist-info/RECORD
