Metadata-Version: 2.1
Name: hello-emoji
Version: 0.0.3
Summary: Simple Hello emoji generator.
Author-email: Afiz <afizshaik@gmail.com>
License: Copyright (c) 2022 Afiz Shaik        
Project-URL: Homepage, https://github.com/afizs/hello-emoji
Project-URL: Bug Tracker, https://github.com/afizs/hello-emoji/issues
Classifier: Programming Language :: Python :: 3
Classifier: License :: OSI Approved :: MIT License
Classifier: Operating System :: OS Independent
Requires-Python: >=3.7
License-File: LICENSE
